{
  "type": "Feature",
  "properties": {
    "gn:admin1_code":"18",
    "gn:asciiname":"Wittiehede Ston",
    "gn:country_code":"SR",
    "gn:dem":97,
    "gn:feature_class":"P",
    "gn:feature_code":"PPL",
    "gn:name":"Wittiehede Ston",
    "gn:population":0,
    "gn:timezone":"America/Paramaribo",
    "iso:country":"SR",
    "wof:name":"Wittiehede Ston",
    "wof:placetype":"locality"
},
  "geometry": {"coordinates":[-55.68333000000001,4.58333],"type":"Point"}
}