{
  "type": "Feature",
  "properties": {
    "gn:admin1_code":"18",
    "gn:asciiname":"Donderkamp",
    "gn:country_code":"SR",
    "gn:dem":13,
    "gn:feature_class":"P",
    "gn:feature_code":"PPL",
    "gn:name":"Donderkamp",
    "gn:population":0,
    "gn:timezone":"America/Paramaribo",
    "iso:country":"SR",
    "name:nld_x_preferred":[
        "Donderkamp"
    ],
    "wof:name":"Donderkamp",
    "wof:placetype":"locality"
},
  "geometry": {"coordinates":[-56.35455,5.34197],"type":"Point"}
}