{
  "type": "Feature",
  "properties": {
    "gn:admin1_code":"18",
    "gn:asciiname":"Malaitawa",
    "gn:country_code":"SR",
    "gn:dem":147,
    "gn:feature_class":"P",
    "gn:feature_code":"PPL",
    "gn:name":"Malaitawa",
    "gn:population":0,
    "gn:timezone":"America/Paramaribo",
    "iso:country":"SR",
    "wof:name":"Malaitawa",
    "wof:placetype":"locality"
},
  "geometry": {"coordinates":[-54.21666999999999,3.13333],"type":"Point"}
}