{
  "type": "Feature",
  "properties": {
    "gn:admin1_code":"12",
    "gn:asciiname":"Mary's Hope",
    "gn:country_code":"SR",
    "gn:dem":4,
    "gn:feature_class":"P",
    "gn:feature_code":"PPL",
    "gn:name":"Mary\u2019s Hope",
    "gn:population":0,
    "gn:timezone":"America/Paramaribo",
    "iso:country":"SR",
    "name:nld_x_preferred":[
        "Mary\u2019s Hope"
    ],
    "wof:name":"Mary's Hope",
    "wof:placetype":"locality"
},
  "geometry": {"coordinates":[-56.30803,5.87049],"type":"Point"}
}