{
  "type": "Feature",
  "properties": {
    "gn:admin1_code":"18",
    "gn:asciiname":"Heidoti",
    "gn:country_code":"SR",
    "gn:dem":44,
    "gn:feature_class":"P",
    "gn:feature_code":"PPL",
    "gn:name":"Heidoti",
    "gn:population":0,
    "gn:timezone":"America/Paramaribo",
    "iso:country":"SR",
    "wof:name":"Heidoti",
    "wof:placetype":"locality"
},
  "geometry": {"coordinates":[-55.56667,4.86667],"type":"Point"}
}