{
  "type": "Feature",
  "properties": {
    "gn:admin1_code":"10",
    "gn:asciiname":"Afobaka",
    "gn:country_code":"SR",
    "gn:dem":37,
    "gn:feature_class":"P",
    "gn:feature_code":"PPL",
    "gn:name":"Afobaka",
    "gn:population":0,
    "gn:timezone":"America/Paramaribo",
    "iso:country":"SR",
    "name:deu_x_preferred":[
        "Afobaka"
    ],
    "name:jpn_x_preferred":[
        "\u30a2\u30db\u30d0\u30c3\u30ab"
    ],
    "name:nld_x_preferred":[
        "Afobaka"
    ],
    "name:spa_x_preferred":[
        "Afobaka"
    ],
    "name:und_x_variant":[
        "Affobakka",
        "Afobaka"
    ],
    "wof:name":"Afobaka",
    "wof:placetype":"locality"
},
  "geometry": {"coordinates":[-54.99851,4.99383],"type":"Point"}
}