{
  "type": "Feature",
  "properties": {
    "gn:admin1_code":"18",
    "gn:asciiname":"Misalibiekondre",
    "gn:country_code":"SR",
    "gn:dem":27,
    "gn:feature_class":"P",
    "gn:feature_code":"PPL",
    "gn:name":"Misalibiekondre",
    "gn:population":0,
    "gn:timezone":"America/Paramaribo",
    "iso:country":"SR",
    "name:und_x_variant":[
        "Misalibi",
        "Misalibiekondre"
    ],
    "wof:name":"Misalibiekondre",
    "wof:placetype":"locality"
},
  "geometry": {"coordinates":[-55.53954,4.93838],"type":"Point"}
}