{
  "type": "Feature",
  "properties": {
    "iso:country":"SR",
    "name:afr_x_preferred":[
        "Zoelen"
    ],
    "name:fra_x_preferred":[
        "Zoelen"
    ],
    "name:nld_x_preferred":[
        "Zoelen"
    ],
    "name:por_x_preferred":[
        "Zoelen"
    ],
    "name:zho_min_nan_x_preferred":[
        "Zoelen"
    ],
    "qs:gn_country":"SR",
    "qs:gn_fcode":"PPL",
    "qs:gn_pop":0,
    "qs:name":"Zoelen",
    "qs:name_adm0":"Suriname",
    "qs:name_adm1":"Commewijne",
    "qs:photos":302,
    "qs:photos_1k":61,
    "qs:photos_9k":1,
    "qs:photos_9r":5,
    "qs:photos_all":302,
    "qs:photos_sr":5,
    "qs:placetype":"Town",
    "qs:pop_sr":"0",
    "qs:woe_adm0":23424913,
    "wd:wordcount":165,
    "wof:name":"Zoelen",
    "wof:placetype":"locality"
},
  "geometry": {"coordinates":[-55.06667,5.88333],"type":"Point"}
}