{
  "type": "Feature",
  "properties": {
    "gn:country":"SR",
    "gn:fcode":"PPLA",
    "gn:population":1685,
    "iso:country":"SR",
    "name:ara_x_preferred":[
        "\u062a\u0648\u062a\u0646\u064a\u0633"
    ],
    "name:ben_x_preferred":[
        "\u099f\u099f\u09a8\u09c7\u09b8"
    ],
    "name:ell_x_preferred":[
        "\u03a4\u03cc\u03c4\u03bd\u03b5\u03c2"
    ],
    "name:fas_x_preferred":[
        "\u062a\u0648\u062a\u0646\u0633"
    ],
    "name:heb_x_preferred":[
        "\u05d8\u05e8\u05d5\u05d8\u05e0\u05e1"
    ],
    "name:hin_x_preferred":[
        "\u091f\u094b\u091f\u0928\u0947\u0938"
    ],
    "name:hun_x_preferred":[
        "Totness"
    ],
    "name:ind_x_preferred":[
        "Totness"
    ],
    "name:swe_x_preferred":[
        "Totness"
    ],
    "name:tur_x_preferred":[
        "Totness"
    ],
    "name:und_x_variant":[
        "Coronie"
    ],
    "name:vie_x_preferred":[
        "Totness"
    ],
    "name:zho_cn_x_preferred":[
        "\u6258\u7279\u5185\u65af"
    ],
    "name:zho_tw_x_preferred":[
        "\u6258\u5c3c\u65af"
    ],
    "ne:ADM0CAP":0.0,
    "ne:ADM0NAME":"Suriname",
    "ne:ADM0_A3":"SUR",
    "ne:ADM1NAME":"Coronie",
    "ne:ADMIN1_COD":12,
    "ne:CAPALT":0,
    "ne:CHANGED":0,
    "ne:CHECKME":0,
    "ne:COMPARE":0,
    "ne:DIFFASCII":0,
    "ne:ELEVATION":0.0,
    "ne:FEATURECLA":"Admin-1 capital",
    "ne:FEATURE_CL":"P",
    "ne:FEATURE_CO":"PPL",
    "ne:GEONAMEID":3382867,
    "ne:GEONAMESNO":"Geonames ascii name + lat.d + long.d matching.",
    "ne:GN_ASCII":"Totness",
    "ne:GN_POP":1685,
    "ne:GTOPO30":1.0,
    "ne:ISO_A2":"SR",
    "ne:LABELRANK":8,
    "ne:LATITUDE":5.890427,
    "ne:LONGITUDE":-56.319984,
    "ne:LS_MATCH":1,
    "ne:LS_NAME":"Totness",
    "ne:MAX_AREAKM":3.0,
    "ne:MAX_AREAMI":1.0,
    "ne:MAX_BBXMAX":-56.325,
    "ne:MAX_BBXMIN":-56.341667,
    "ne:MAX_BBYMAX":5.883333,
    "ne:MAX_BBYMIN":5.866667,
    "ne:MAX_NATSCA":20.0,
    "ne:MAX_PERKM":7.0,
    "ne:MAX_PERMI":5.0,
    "ne:MAX_POP10":1251,
    "ne:MAX_POP20":1251,
    "ne:MAX_POP300":0,
    "ne:MAX_POP310":0,
    "ne:MAX_POP50":0,
    "ne:MEAN_BBXC":-56.333333,
    "ne:MEAN_BBYC":5.875,
    "ne:MEGACITY":0,
    "ne:MIN_AREAKM":3.0,
    "ne:MIN_AREAMI":1.0,
    "ne:MIN_BBXMAX":-56.325,
    "ne:MIN_BBXMIN":-56.341667,
    "ne:MIN_BBYMAX":5.883333,
    "ne:MIN_BBYMIN":5.866667,
    "ne:MIN_PERKM":7.0,
    "ne:MIN_PERMI":5.0,
    "ne:NAME":"Totness",
    "ne:NAMEASCII":"Totness",
    "ne:NAMEDIFF":0,
    "ne:NATSCALE":20,
    "ne:POP1950":0,
    "ne:POP1955":0,
    "ne:POP1960":0,
    "ne:POP1965":0,
    "ne:POP1970":0,
    "ne:POP1975":0,
    "ne:POP1980":0,
    "ne:POP1985":0,
    "ne:POP1990":0,
    "ne:POP1995":0,
    "ne:POP2000":0,
    "ne:POP2005":0,
    "ne:POP2010":0,
    "ne:POP2015":0,
    "ne:POP2020":0,
    "ne:POP2025":0,
    "ne:POP2050":0,
    "ne:POP_MAX":1685,
    "ne:POP_MIN":1251,
    "ne:POP_OTHER":0,
    "ne:RANK_MAX":3,
    "ne:RANK_MIN":3,
    "ne:SCALERANK":7,
    "ne:SOV0NAME":"Suriname",
    "ne:SOV_A3":"SUR",
    "ne:TIMEZONE":"America/Paramaribo",
    "ne:UN_FID":0,
    "ne:UN_LAT":0.0,
    "ne:UN_LONG":0.0,
    "ne:WORLDCITY":0,
    "qs:name":"Totness",
    "qs:photos_9r":0,
    "qs:photos_sr":0,
    "qs:pop_sr":"3",
    "wd:wordcount":59,
    "wof:name":"Totness",
    "wof:placetype":"locality",
    "wof:population":1685
},
  "geometry": {"coordinates":[-56.31667,5.88333],"type":"Point"}
}