{
  "type": "Feature",
  "properties": {
    "gn:admin1_code":"19",
    "gn:asciiname":"KL Poika",
    "gn:country_code":"SR",
    "gn:dem":16,
    "gn:feature_class":"P",
    "gn:feature_code":"PPL",
    "gn:name":"KL Poika",
    "gn:population":0,
    "gn:timezone":"America/Paramaribo",
    "iso:country":"SR",
    "name:nld_x_preferred":[
        "KL Poika"
    ],
    "name:und_x_variant":[
        "Klein Poika (1)",
        "Klein Poika"
    ],
    "wof:name":"KL Poika",
    "wof:placetype":"locality"
},
  "geometry": {"coordinates":[-55.34261,5.68145],"type":"Point"}
}