{
  "type": "Feature",
  "properties": {
    "gn:admin1_code":"18",
    "gn:asciiname":"Cajana",
    "gn:country_code":"SR",
    "gn:dem":106,
    "gn:feature_class":"P",
    "gn:feature_code":"PPL",
    "gn:name":"Cajana",
    "gn:population":0,
    "gn:timezone":"America/Paramaribo",
    "iso:country":"SR",
    "name:und_x_variant":[
        "Kajana"
    ],
    "wof:name":"Cajana",
    "wof:placetype":"locality"
},
  "geometry": {"coordinates":[-55.57261999999999,3.90116],"type":"Point"}
}