{
  "type": "Feature",
  "properties": {
    "gn:admin1_code":"18",
    "gn:asciiname":"Brokolonko",
    "gn:country_code":"SR",
    "gn:dem":29,
    "gn:feature_class":"P",
    "gn:feature_code":"PPL",
    "gn:name":"Brokolonko",
    "gn:population":0,
    "gn:timezone":"America/Paramaribo",
    "iso:country":"SR",
    "name:nld_x_preferred":[
        "Brokolonko"
    ],
    "wof:name":"Brokolonko",
    "wof:placetype":"locality"
},
  "geometry": {"coordinates":[-55.54268,5.03275],"type":"Point"}
}