{
  "type": "Feature",
  "properties": {
    "gn:admin1_code":"18",
    "gn:asciiname":"Vertrouwen",
    "gn:cc2":"SR",
    "gn:country_code":"SR",
    "gn:dem":110,
    "gn:feature_class":"P",
    "gn:feature_code":"PPL",
    "gn:name":"Vertrouwen",
    "gn:population":0,
    "gn:timezone":"America/Paramaribo",
    "iso:country":"SR",
    "name:und_x_variant":[
        "Monbobasoe",
        "Vertrouw",
        "Mombabasoe",
        "Monbabasoe",
        "Mambabasoe",
        "Vertrouwen"
    ],
    "wof:name":"Vertrouwen",
    "wof:placetype":"locality"
},
  "geometry": {"coordinates":[-55.78333000000001,4.33333],"type":"Point"}
}