{
  "type": "Feature",
  "properties": {
    "gn:admin1_code":"15",
    "gn:asciiname":"Bloferie",
    "gn:cc2":"SR",
    "gn:country_code":"SR",
    "gn:dem":17,
    "gn:feature_class":"P",
    "gn:feature_code":"PPL",
    "gn:name":"Bloferie",
    "gn:population":0,
    "gn:timezone":"America/Paramaribo",
    "iso:country":"SR",
    "name:und_x_variant":[
        "Vier Hendrikken",
        "De Vier Hendrikken",
        "Bloferie"
    ],
    "wof:name":"Bloferie",
    "wof:placetype":"locality"
},
  "geometry": {"coordinates":[-55.38333000000001,5.61667],"type":"Point"}
}