{
  "type": "Feature",
  "properties": {
    "gn:admin1_code":"11",
    "gn:asciiname":"Laarwijk",
    "gn:country_code":"SR",
    "gn:dem":0,
    "gn:feature_class":"P",
    "gn:feature_code":"PPL",
    "gn:name":"Laarwijk",
    "gn:population":0,
    "gn:timezone":"America/Paramaribo",
    "iso:country":"SR",
    "name:nld_x_preferred":[
        "Laarwijk"
    ],
    "name:urd_x_preferred":[
        "\u0644\u0627\u0631\u0648\u06cc\u062c\u06a9"
    ],
    "wof:name":"Laarwijk",
    "wof:placetype":"locality"
},
  "geometry": {"coordinates":[-55.07368,5.70168],"type":"Point"}
}