{
  "type": "Feature",
  "properties": {
    "gn:admin1_code":"11",
    "gn:asciiname":"Laarwijk",
    "gn:country_code":"SR",
    "gn:dem":0,
    "gn:feature_class":"P",
    "gn:feature_code":"PPL",
    "gn:name":"Laarwijk",
    "gn:population":0,
    "gn:timezone":"America/Paramaribo",
    "iso:country":"SR",
    "wof:name":"Laarwijk",
    "wof:placetype":"locality"
},
  "geometry": {"coordinates":[-55.07368,5.70168],"type":"Point"}
}