{
  "type": "Feature",
  "properties": {
    "gn:admin1_code":"13",
    "gn:asciiname":"Jaimeskondre",
    "gn:country_code":"SR",
    "gn:dem":23,
    "gn:feature_class":"P",
    "gn:feature_code":"PPL",
    "gn:name":"Jaimeskondre",
    "gn:population":0,
    "gn:timezone":"America/Paramaribo",
    "iso:country":"SR",
    "name:und_x_variant":[
        "James Kondre",
        "Jaimeskondre"
    ],
    "wof:name":"Jaimeskondre",
    "wof:placetype":"locality"
},
  "geometry": {"coordinates":[-54.17464,5.35681],"type":"Point"}
}