{
  "type": "Feature",
  "properties": {
    "gn:admin1_code":"18",
    "gn:asciiname":"Abontjeman",
    "gn:country_code":"SR",
    "gn:dem":43,
    "gn:feature_class":"P",
    "gn:feature_code":"PPL",
    "gn:name":"Abontjeman",
    "gn:population":0,
    "gn:timezone":"America/Paramaribo",
    "iso:country":"SR",
    "name:fas_x_preferred":[
        "\u0627\u0628\u0627\u0646\u062a\u062c\u0645\u0627\u0646"
    ],
    "wof:name":"Abontjeman",
    "wof:placetype":"locality"
},
  "geometry": {"coordinates":[-54.996,4.86313],"type":"Point"}
}