{
  "type": "Feature",
  "properties": {
    "gn:admin1_code":"11",
    "gn:asciiname":"Clevia",
    "gn:country_code":"SR",
    "gn:dem":1,
    "gn:feature_class":"P",
    "gn:feature_code":"PPL",
    "gn:name":"Clevia",
    "gn:population":0,
    "gn:timezone":"America/Paramaribo",
    "iso:country":"SR",
    "wof:name":"Clevia",
    "wof:placetype":"locality"
},
  "geometry": {"coordinates":[-55.1158,5.86181],"type":"Point"}
}