{
  "type": "Feature",
  "properties": {
    "iso:country":"SR",
    "name:eng_x_preferred":[
        "Cottica"
    ],
    "name:fra_x_preferred":[
        "Cottica"
    ],
    "name:jpn_x_preferred":[
        "\u30b3\u30c3\u30c6\u30a3\u30ab"
    ],
    "name:kor_x_preferred":[
        "\ucf54\ud2f0\uce74"
    ],
    "name:lit_x_preferred":[
        "Kotika"
    ],
    "name:nld_x_preferred":[
        "Cottica"
    ],
    "name:por_x_preferred":[
        "Cottica"
    ],
    "name:ron_x_preferred":[
        "Cottica"
    ],
    "name:spa_x_preferred":[
        "Cottica"
    ],
    "name:srn_x_preferred":[
        "Cottica"
    ],
    "ne:ADM0CAP":0.0,
    "ne:ADM0NAME":"Suriname",
    "ne:ADM0_A3":"SUR",
    "ne:ADM1NAME":"Sipaliwini",
    "ne:ADMIN1_COD":0,
    "ne:CAPALT":0,
    "ne:CHANGED":0,
    "ne:CHECKME":0,
    "ne:COMPARE":0,
    "ne:DIFFASCII":0,
    "ne:ELEVATION":0.0,
    "ne:FEATURECLA":"Populated place",
    "ne:GEONAMEID":-1,
    "ne:GEONAMESNO":"Top 50 ranks with no GeoNames match due to small population, not in GeoNames, or poor NEV placement.",
    "ne:GN_POP":0,
    "ne:GTOPO30":0.0,
    "ne:ISO_A2":"SR",
    "ne:LABELRANK":8,
    "ne:LATITUDE":3.850009,
    "ne:LONGITUDE":-54.233289,
    "ne:LS_MATCH":0,
    "ne:LS_NAME":"Cottica",
    "ne:MAX_AREAKM":0.0,
    "ne:MAX_AREAMI":0.0,
    "ne:MAX_BBXMAX":0.0,
    "ne:MAX_BBXMIN":0.0,
    "ne:MAX_BBYMAX":0.0,
    "ne:MAX_BBYMIN":0.0,
    "ne:MAX_NATSCA":0.0,
    "ne:MAX_PERKM":0.0,
    "ne:MAX_PERMI":0.0,
    "ne:MAX_POP10":0,
    "ne:MAX_POP20":0,
    "ne:MAX_POP300":0,
    "ne:MAX_POP310":0,
    "ne:MAX_POP50":0,
    "ne:MEAN_BBXC":0.0,
    "ne:MEAN_BBYC":0.0,
    "ne:MEGACITY":0,
    "ne:MIN_AREAKM":0.0,
    "ne:MIN_AREAMI":0.0,
    "ne:MIN_BBXMAX":0.0,
    "ne:MIN_BBXMIN":0.0,
    "ne:MIN_BBYMAX":0.0,
    "ne:MIN_BBYMIN":0.0,
    "ne:MIN_PERKM":0.0,
    "ne:MIN_PERMI":0.0,
    "ne:NAME":"Cottica",
    "ne:NAMEASCII":"Cottica",
    "ne:NAMEDIFF":0,
    "ne:NATSCALE":50,
    "ne:POP1950":0,
    "ne:POP1955":0,
    "ne:POP1960":0,
    "ne:POP1965":0,
    "ne:POP1970":0,
    "ne:POP1975":0,
    "ne:POP1980":0,
    "ne:POP1985":0,
    "ne:POP1990":0,
    "ne:POP1995":0,
    "ne:POP2000":0,
    "ne:POP2005":0,
    "ne:POP2010":0,
    "ne:POP2015":0,
    "ne:POP2020":0,
    "ne:POP2025":0,
    "ne:POP2050":0,
    "ne:POP_MAX":29210,
    "ne:POP_MIN":20000,
    "ne:POP_OTHER":0,
    "ne:RANK_MAX":7,
    "ne:RANK_MIN":6,
    "ne:SCALERANK":4,
    "ne:SOV0NAME":"Suriname",
    "ne:SOV_A3":"SUR",
    "ne:UN_FID":0,
    "ne:UN_LAT":0.0,
    "ne:UN_LONG":0.0,
    "ne:WORLDCITY":0,
    "ne:min_zoom":5.6,
    "wof:name":"Cottica",
    "wof:placetype":"locality"
},
  "geometry": {"coordinates":[-54.2332894303425,3.85000917451094],"type":"Point"}
}