{
  "type": "Feature",
  "properties": {
    "gn:admin1_code":"18",
    "gn:asciiname":"Asoenoebo",
    "gn:country_code":"SR",
    "gn:dem":74,
    "gn:feature_class":"P",
    "gn:feature_code":"PPL",
    "gn:name":"Asoenoebo",
    "gn:population":0,
    "gn:timezone":"America/Paramaribo",
    "iso:country":"SR",
    "name:nld_x_preferred":[
        "Asoenoebo"
    ],
    "wof:name":"Asoenoebo",
    "wof:placetype":"locality"
},
  "geometry": {"coordinates":[-55.68145,4.61623],"type":"Point"}
}