{
  "type": "Feature",
  "properties": {
    "gn:admin1_code":"10",
    "gn:asciiname":"Krikie",
    "gn:country_code":"SR",
    "gn:dem":43,
    "gn:feature_class":"P",
    "gn:feature_code":"PPL",
    "gn:name":"Krikie",
    "gn:population":0,
    "gn:timezone":"America/Paramaribo",
    "iso:country":"SR",
    "name:nld_x_preferred":[
        "Krikie"
    ],
    "wof:name":"Krikie",
    "wof:placetype":"locality"
},
  "geometry": {"coordinates":[-55.00746,4.94854],"type":"Point"}
}