{
  "type": "Feature",
  "properties": {
    "gn:admin1_code":"13",
    "gn:asciiname":"Adjoema Kondre",
    "gn:country_code":"SR",
    "gn:dem":23,
    "gn:feature_class":"P",
    "gn:feature_code":"PPL",
    "gn:name":"Adjoema Kondre",
    "gn:population":0,
    "gn:timezone":"America/Paramaribo",
    "iso:country":"SR",
    "name:nld_x_preferred":[
        "Adjoema Kondre"
    ],
    "name:und_x_variant":[
        "Adjamoe-kondre",
        "Adjoemakondre"
    ],
    "wof:name":"Adjoema Kondre",
    "wof:placetype":"locality"
},
  "geometry": {"coordinates":[-54.26478,5.58507],"type":"Point"}
}