{
  "type": "Feature",
  "properties": {
    "iso:country":"SR",
    "name:eng_x_preferred":[
        "Paloemeu"
    ],
    "name:jpn_x_preferred":[
        "\u30d1\u30eb\u30e1\u30a6"
    ],
    "name:nld_x_preferred":[
        "Paloemeu"
    ],
    "qs:gn_pop":0,
    "qs:name":"Palumeu",
    "qs:name_adm0":"Suriname",
    "qs:name_adm1":"Sipaliwini",
    "qs:photos":67,
    "qs:photos_1k":14,
    "qs:photos_9k":1,
    "qs:photos_9r":2,
    "qs:photos_all":67,
    "qs:photos_sr":2,
    "qs:placetype":"Town",
    "qs:pop_sr":"0",
    "qs:woe_adm0":23424913,
    "wd:wordcount":204,
    "wof:name":"Palumeu",
    "wof:placetype":"locality"
},
  "geometry": {"coordinates":[-55.446109,3.345579],"type":"Point"}
}