{
  "type": "Feature",
  "properties": {
    "gn:admin1_code":"13",
    "gn:asciiname":"Lantiwei",
    "gn:country_code":"SR",
    "gn:dem":22,
    "gn:feature_class":"P",
    "gn:feature_code":"PPL",
    "gn:name":"Lantiwei",
    "gn:population":0,
    "gn:timezone":"America/Paramaribo",
    "iso:country":"SR",
    "name:nld_x_preferred":[
        "Lantiwei"
    ],
    "wof:name":"Lantiwei",
    "wof:placetype":"locality"
},
  "geometry": {"coordinates":[-54.40333,5.78275],"type":"Point"}
}