{
  "type": "Feature",
  "properties": {
    "gn:admin1_code":"18",
    "gn:asciiname":"Dahomey",
    "gn:cc2":"SR",
    "gn:country_code":"SR",
    "gn:dem":95,
    "gn:feature_class":"P",
    "gn:feature_code":"PPL",
    "gn:name":"Dahomey",
    "gn:population":0,
    "gn:timezone":"America/Paramaribo",
    "iso:country":"SR",
    "name:und_x_variant":[
        "Dahome",
        "Gran Dahomeij",
        "Dahomey"
    ],
    "wof:name":"Dahomey",
    "wof:placetype":"locality"
},
  "geometry": {"coordinates":[-55.46666999999999,4.03333],"type":"Point"}
}