{
  "type": "Feature",
  "properties": {
    "gn:admin1_code":"11",
    "gn:asciiname":"Klaverblad",
    "gn:country_code":"SR",
    "gn:dem":17,
    "gn:feature_class":"P",
    "gn:feature_code":"PPL",
    "gn:name":"Klaverblad",
    "gn:population":0,
    "gn:timezone":"America/Paramaribo",
    "iso:country":"SR",
    "name:nld_x_preferred":[
        "Klaverblad"
    ],
    "wof:name":"Klaverblad",
    "wof:placetype":"locality"
},
  "geometry": {"coordinates":[-55.03652,5.65797],"type":"Point"}
}