{
  "type": "Feature",
  "properties": {
    "gn:admin1_code":"12",
    "gn:asciiname":"Sarah",
    "gn:country_code":"SR",
    "gn:dem":11,
    "gn:feature_class":"P",
    "gn:feature_code":"PPL",
    "gn:name":"Sarah",
    "gn:population":0,
    "gn:timezone":"America/Paramaribo",
    "iso:country":"SR",
    "name:ara_x_preferred":[
        "\u0633\u0627\u0631\u0629"
    ],
    "name:arz_x_preferred":[
        "\u0633\u0627\u0631\u0647"
    ],
    "name:ben_x_preferred":[
        "\u09b8\u09be\u09b0\u09be\u09b9"
    ],
    "name:bod_x_preferred":[
        "\u0f66\u0f0b\u0f62\u0f71\u0f0d"
    ],
    "name:bul_x_preferred":[
        "\u0421\u0430\u0440\u0440\u0430"
    ],
    "name:cat_x_preferred":[
        "Sara"
    ],
    "name:ces_x_preferred":[
        "S\u00e1ra"
    ],
    "name:che_x_preferred":[
        "\u0421\u0430\u0440\u0430\u0442"
    ],
    "name:cym_x_preferred":[
        "Sarah"
    ],
    "name:deu_x_preferred":[
        "Sara"
    ],
    "name:diq_x_preferred":[
        "Sare"
    ],
    "name:ell_x_preferred":[
        "\u03a3\u03ac\u03c1\u03b1"
    ],
    "name:epo_x_preferred":[
        "Sara"
    ],
    "name:est_x_preferred":[
        "Saara"
    ],
    "name:eus_x_preferred":[
        "Sara"
    ],
    "name:fas_x_preferred":[
        "\u0633\u0627\u0631\u0627"
    ],
    "name:fin_x_preferred":[
        "Saara"
    ],
    "name:fra_x_preferred":[
        "Sarah"
    ],
    "name:fry_x_preferred":[
        "Sara"
    ],
    "name:heb_x_preferred":[
        "\u05e9\u05e8\u05d4"
    ],
    "name:hrv_x_preferred":[
        "Sara"
    ],
    "name:hun_x_preferred":[
        "S\u00e1ra"
    ],
    "name:ind_x_preferred":[
        "Sara"
    ],
    "name:ita_x_preferred":[
        "Sara"
    ],
    "name:lad_x_preferred":[
        "Sara Imenu"
    ],
    "name:lit_x_preferred":[
        "Sara"
    ],
    "name:mlg_x_preferred":[
        "Saraha"
    ],
    "name:nld_x_preferred":[
        "Sarah"
    ],
    "name:nld_x_variant":[
        "Sara"
    ],
    "name:nno_x_preferred":[
        "Matriarken Sara"
    ],
    "name:nor_x_preferred":[
        "Sara"
    ],
    "name:pol_x_preferred":[
        "Sara"
    ],
    "name:por_x_preferred":[
        "Sara"
    ],
    "name:ron_x_preferred":[
        "Sara"
    ],
    "name:rus_x_preferred":[
        "\u0421\u0430\u0440\u0440\u0430"
    ],
    "name:sco_x_preferred":[
        "Saurah"
    ],
    "name:spa_x_preferred":[
        "Sara"
    ],
    "name:srp_x_preferred":[
        "\u0421\u0430\u0440\u0430"
    ],
    "name:swa_x_preferred":[
        "Sara"
    ],
    "name:swe_x_preferred":[
        "Sara"
    ],
    "name:tam_x_preferred":[
        "\u0b9a\u0bbe\u0bb0\u0bbe\u0bb3\u0bcd"
    ],
    "name:tel_x_preferred":[
        "\u0c39\u0c3e\u0c1c\u0c30\u0c3e"
    ],
    "name:tgk_x_preferred":[
        "\u0421\u043e\u0440\u043e"
    ],
    "name:tgl_x_preferred":[
        "Sarai"
    ],
    "name:tur_x_preferred":[
        "Sare"
    ],
    "name:ukr_x_preferred":[
        "\u0421\u0430\u0440\u0430"
    ],
    "name:urd_x_preferred":[
        "\u0633\u0627\u0631\u06c1"
    ],
    "name:vie_x_preferred":[
        "Sarah"
    ],
    "name:yid_x_preferred":[
        "\u05e9\u05e8\u05d4"
    ],
    "wof:name":"Sarah",
    "wof:placetype":"locality"
},
  "geometry": {"coordinates":[-56.37311,5.88993],"type":"Point"}
}