{
  "type": "Feature",
  "properties": {
    "gn:admin1_code":"12",
    "gn:asciiname":"Sarah",
    "gn:country_code":"SR",
    "gn:dem":11,
    "gn:feature_class":"P",
    "gn:feature_code":"PPL",
    "gn:name":"Sarah",
    "gn:population":0,
    "gn:timezone":"America/Paramaribo",
    "iso:country":"SR",
    "name:nld_x_preferred":[
        "Sarah"
    ],
    "wof:name":"Sarah",
    "wof:placetype":"locality"
},
  "geometry": {"coordinates":[-56.37311,5.88993],"type":"Point"}
}