{
  "type": "Feature",
  "properties": {
    "gn:admin1_code":"15",
    "gn:asciiname":"Cassipora",
    "gn:country_code":"SR",
    "gn:dem":22,
    "gn:feature_class":"P",
    "gn:feature_code":"PPL",
    "gn:name":"Cassipora",
    "gn:population":0,
    "gn:timezone":"America/Paramaribo",
    "iso:country":"SR",
    "name:und_x_variant":[
        "Casipora",
        "Cassipora"
    ],
    "wof:name":"Cassipora",
    "wof:placetype":"locality"
},
  "geometry": {"coordinates":[-54.95377,5.39652],"type":"Point"}
}