{
  "type": "Feature",
  "properties": {
    "gn:admin1_code":"15",
    "gn:asciiname":"Mattawaribo",
    "gn:cc2":"SR",
    "gn:country_code":"SR",
    "gn:dem":10,
    "gn:feature_class":"P",
    "gn:feature_code":"PPL",
    "gn:name":"Mattawaribo",
    "gn:population":0,
    "gn:timezone":"America/Paramaribo",
    "iso:country":"SR",
    "name:und_x_variant":[
        "Mattewaribo",
        "Matawaribo",
        "Mattawaribo"
    ],
    "wof:name":"Mattawaribo",
    "wof:placetype":"locality"
},
  "geometry": {"coordinates":[-55.16667,5.53333],"type":"Point"}
}