{
  "type": "Feature",
  "properties": {
    "gn:admin1_code":"18",
    "gn:asciiname":"Nason",
    "gn:country_code":"SR",
    "gn:dem":43,
    "gn:feature_class":"P",
    "gn:feature_code":"PPL",
    "gn:name":"Nason",
    "gn:population":0,
    "gn:timezone":"America/Paramaribo",
    "iso:country":"SR",
    "name:deu_x_preferred":[
        "Nason"
    ],
    "name:und_x_variant":[
        "Americankondre"
    ],
    "wof:name":"Nason",
    "wof:placetype":"locality"
},
  "geometry": {"coordinates":[-54.47676,4.81827],"type":"Point"}
}