{
  "type": "Feature",
  "properties": {
    "gn:admin1_code":"18",
    "gn:asciiname":"Saje",
    "gn:country_code":"SR",
    "gn:dem":82,
    "gn:feature_class":"P",
    "gn:feature_code":"PPL",
    "gn:name":"Saje",
    "gn:population":0,
    "gn:timezone":"America/Paramaribo",
    "iso:country":"SR",
    "wof:name":"Saje",
    "wof:placetype":"locality"
},
  "geometry": {"coordinates":[-54.56667,4.18333],"type":"Point"}
}