{
  "type": "Feature",
  "properties": {
    "gn:admin1_code":"15",
    "gn:asciiname":"Kopi Ondroo",
    "gn:country_code":"SR",
    "gn:dem":23,
    "gn:feature_class":"P",
    "gn:feature_code":"PPL",
    "gn:name":"Kopi Ondroo",
    "gn:population":0,
    "gn:timezone":"America/Paramaribo",
    "iso:country":"SR",
    "name:und_x_variant":[
        "Kopi Ondro",
        "Kopi Ondroo"
    ],
    "wof:name":"Kopi Ondroo",
    "wof:placetype":"locality"
},
  "geometry": {"coordinates":[-54.68493,5.34913],"type":"Point"}
}