{
  "type": "Feature",
  "properties": {
    "gn:admin1_code":"18",
    "gn:asciiname":"Fransman Landing",
    "gn:country_code":"SR",
    "gn:dem":62,
    "gn:feature_class":"P",
    "gn:feature_code":"PPL",
    "gn:name":"Fransman Landing",
    "gn:population":0,
    "gn:timezone":"America/Paramaribo",
    "iso:country":"SR",
    "wof:name":"Fransman Landing",
    "wof:placetype":"locality"
},
  "geometry": {"coordinates":[-57.03966,5.19109],"type":"Point"}
}