{
  "type": "Feature",
  "properties": {
    "gn:admin1_code":"10",
    "gn:asciiname":"Sesebiase",
    "gn:country_code":"SR",
    "gn:dem":17,
    "gn:feature_class":"P",
    "gn:feature_code":"PPL",
    "gn:name":"Sesebiase",
    "gn:population":0,
    "gn:timezone":"America/Paramaribo",
    "iso:country":"SR",
    "name:nld_x_preferred":[
        "Sesebiase"
    ],
    "wof:name":"Sesebiase",
    "wof:placetype":"locality"
},
  "geometry": {"coordinates":[-54.9929,5.15609],"type":"Point"}
}