{
  "type": "Feature",
  "properties": {
    "gn:admin1_code":"19",
    "gn:asciiname":"Vredenburg",
    "gn:country_code":"SR",
    "gn:dem":6,
    "gn:feature_class":"P",
    "gn:feature_code":"PPL",
    "gn:name":"Vredenburg",
    "gn:population":0,
    "gn:timezone":"America/Paramaribo",
    "iso:country":"SR",
    "name:afr_x_preferred":[
        "Vredenburg"
    ],
    "name:deu_x_preferred":[
        "Vredenburg"
    ],
    "name:est_x_preferred":[
        "Vredenburg"
    ],
    "name:mlg_x_preferred":[
        "Vredenburg"
    ],
    "name:nld_x_preferred":[
        "Vredenburg"
    ],
    "name:nso_x_preferred":[
        "Vredenburg"
    ],
    "name:ron_x_preferred":[
        "Vredenburg"
    ],
    "name:rus_x_preferred":[
        "\u0424\u0440\u0438\u0434\u0435\u043d\u0431\u0443\u0440\u0433"
    ],
    "name:zho_x_preferred":[
        "\u5f17\u91cc\u767b\u5821"
    ],
    "wof:name":"Vredenburg",
    "wof:placetype":"locality"
},
  "geometry": {"coordinates":[-55.15483,5.72324],"type":"Point"}
}