{
  "type": "Feature",
  "properties": {
    "gn:admin1_code":"13",
    "gn:asciiname":"Akroikondre",
    "gn:country_code":"SR",
    "gn:dem":19,
    "gn:feature_class":"P",
    "gn:feature_code":"PPL",
    "gn:name":"Akroikondre",
    "gn:population":0,
    "gn:timezone":"America/Paramaribo",
    "iso:country":"SR",
    "name:nld_x_preferred":[
        "Akroikondre"
    ],
    "wof:name":"Akroikondre",
    "wof:placetype":"locality"
},
  "geometry": {"coordinates":[-54.09406,5.46029],"type":"Point"}
}