{
  "type": "Feature",
  "properties": {
    "gn:admin1_code":"15",
    "gn:asciiname":"Bottriekoe Santi",
    "gn:country_code":"SR",
    "gn:dem":34,
    "gn:feature_class":"P",
    "gn:feature_code":"PPL",
    "gn:name":"Bottriekoe Santi",
    "gn:population":0,
    "gn:timezone":"America/Paramaribo",
    "iso:country":"SR",
    "name:nld_x_preferred":[
        "Bottriekoe Santi"
    ],
    "wof:name":"Bottriekoe Santi",
    "wof:placetype":"locality"
},
  "geometry": {"coordinates":[-55.54785,5.06244],"type":"Point"}
}