{
  "type": "Feature",
  "properties": {
    "gn:admin1_code":"18",
    "gn:asciiname":"Gonoe",
    "gn:country_code":"SR",
    "gn:dem":30,
    "gn:feature_class":"P",
    "gn:feature_code":"PPL",
    "gn:name":"Gonoe",
    "gn:population":0,
    "gn:timezone":"America/Paramaribo",
    "iso:country":"SR",
    "name:nld_x_preferred":[
        "Gonoe"
    ],
    "wof:name":"Gonoe",
    "wof:placetype":"locality"
},
  "geometry": {"coordinates":[-54.42261,5.08565],"type":"Point"}
}