{
  "type": "Feature",
  "properties": {
    "gn:admin1_code":"18",
    "gn:asciiname":"Pokigron",
    "gn:country_code":"SR",
    "gn:dem":71,
    "gn:feature_class":"P",
    "gn:feature_code":"PPL",
    "gn:name":"Pokigron",
    "gn:population":0,
    "gn:timezone":"America/Paramaribo",
    "iso:country":"SR",
    "wof:name":"Pokigron",
    "wof:placetype":"locality"
},
  "geometry": {"coordinates":[-55.36971,4.49232],"type":"Point"}
}