{
  "type": "Feature",
  "properties": {
    "gn:admin1_code":"18",
    "gn:asciiname":"Pokigron",
    "gn:country_code":"SR",
    "gn:dem":71,
    "gn:feature_class":"P",
    "gn:feature_code":"PPL",
    "gn:name":"Pokigron",
    "gn:population":0,
    "gn:timezone":"America/Paramaribo",
    "iso:country":"SR",
    "name:deu_x_preferred":[
        "Pokigron"
    ],
    "name:kor_x_preferred":[
        "\ud3ec\ud0a4\uadf8\ub860"
    ],
    "name:nld_x_preferred":[
        "Pokigron"
    ],
    "name:ron_x_preferred":[
        "Pokigron"
    ],
    "name:spa_x_preferred":[
        "Pokigron"
    ],
    "name:srn_x_preferred":[
        "Pokigron"
    ],
    "wof:name":"Pokigron",
    "wof:placetype":"locality"
},
  "geometry": {"coordinates":[-55.36971,4.49232],"type":"Point"}
}