{
  "type": "Feature",
  "properties": {
    "gn:admin1_code":"18",
    "gn:asciiname":"De Goede Hoop",
    "gn:country_code":"SR",
    "gn:dem":15,
    "gn:feature_class":"P",
    "gn:feature_code":"PPL",
    "gn:name":"De Goede Hoop",
    "gn:population":0,
    "gn:timezone":"America/Paramaribo",
    "iso:country":"SR",
    "name:nld_x_preferred":[
        "De Goede Hoop"
    ],
    "wof:name":"De Goede Hoop",
    "wof:placetype":"locality"
},
  "geometry": {"coordinates":[-55.96391,5.52869],"type":"Point"}
}