{
  "type": "Feature",
  "properties": {
    "gn:admin1_code":"10",
    "gn:asciiname":"Nieuw Lombe",
    "gn:country_code":"SR",
    "gn:dem":12,
    "gn:feature_class":"P",
    "gn:feature_code":"PPL",
    "gn:name":"Nieuw Lomb\u00e9",
    "gn:population":0,
    "gn:timezone":"America/Paramaribo",
    "iso:country":"SR",
    "name:nld_x_preferred":[
        "Nieuw Lomb\u00e9"
    ],
    "wof:name":"Nieuw Lombe",
    "wof:placetype":"locality"
},
  "geometry": {"coordinates":[-55.06797,5.1729],"type":"Point"}
}