{
  "type": "Feature",
  "properties": {
    "gn:admin1_code":"15",
    "gn:asciiname":"Joden Savanna",
    "gn:country_code":"SR",
    "gn:dem":17,
    "gn:feature_class":"P",
    "gn:feature_code":"PPL",
    "gn:name":"Joden Savanna",
    "gn:population":0,
    "gn:timezone":"America/Paramaribo",
    "iso:country":"SR",
    "name:und_x_variant":[
        "Jodensavanne"
    ],
    "wof:name":"Joden Savanna",
    "wof:placetype":"locality"
},
  "geometry": {"coordinates":[-54.98609,5.42029],"type":"Point"}
}