{
  "type": "Feature",
  "properties": {
    "gn:admin1_code":"15",
    "gn:asciiname":"Joden Savanna",
    "gn:country_code":"SR",
    "gn:dem":17,
    "gn:feature_class":"P",
    "gn:feature_code":"PPL",
    "gn:name":"Joden Savanna",
    "gn:population":0,
    "gn:timezone":"America/Paramaribo",
    "iso:country":"SR",
    "name:deu_x_preferred":[
        "Jodensavanne"
    ],
    "name:fin_x_preferred":[
        "Jodensavanne"
    ],
    "name:fra_x_preferred":[
        "Jodensavanne"
    ],
    "name:heb_x_preferred":[
        "\u05d9\u05d5\u05d3\u05e0\u05e1\u05d5\u05d5\u05d0\u05e0\u05d4"
    ],
    "name:ita_x_preferred":[
        "Jodensavanne"
    ],
    "name:nld_x_preferred":[
        "Jodensavanne"
    ],
    "name:por_x_preferred":[
        "Jodensavanne"
    ],
    "name:rus_x_preferred":[
        "\u0419\u043e\u0434\u0435\u043d\u0441\u0430\u0432\u0430\u043d\u043d\u0430"
    ],
    "name:spa_x_preferred":[
        "Jodensavanne"
    ],
    "name:swe_x_preferred":[
        "Jodensavanne"
    ],
    "name:tur_x_preferred":[
        "Jodensavanne"
    ],
    "wof:name":"Joden Savanna",
    "wof:placetype":"locality"
},
  "geometry": {"coordinates":[-54.98609,5.42029],"type":"Point"}
}