{
  "type": "Feature",
  "properties": {
    "gn:admin1_code":"15",
    "gn:asciiname":"Suhoza of Agila",
    "gn:country_code":"SR",
    "gn:dem":8,
    "gn:feature_class":"P",
    "gn:feature_code":"PPL",
    "gn:name":"Suhoza of Agila",
    "gn:population":0,
    "gn:timezone":"America/Paramaribo",
    "iso:country":"SR",
    "name:nld_x_preferred":[
        "Suhoza of Agila"
    ],
    "name:und_x_variant":[
        "Agila",
        "Suhoza"
    ],
    "wof:name":"Suhoza of Agila",
    "wof:placetype":"locality"
},
  "geometry": {"coordinates":[-55.00623,5.35667],"type":"Point"}
}