{
  "type": "Feature",
  "properties": {
    "gn:admin1_code":"15",
    "gn:asciiname":"Copie",
    "gn:country_code":"SR",
    "gn:dem":11,
    "gn:feature_class":"P",
    "gn:feature_code":"PPL",
    "gn:name":"Copie",
    "gn:population":0,
    "gn:timezone":"America/Paramaribo",
    "iso:country":"SR",
    "name:nld_x_preferred":[
        "Copie"
    ],
    "wof:name":"Copie",
    "wof:placetype":"locality"
},
  "geometry": {"coordinates":[-54.80725,5.51058],"type":"Point"}
}