{
  "type": "Feature",
  "properties": {
    "gn:admin1_code":"13",
    "gn:asciiname":"Ricanau Moffo",
    "gn:cc2":"SR",
    "gn:country_code":"SR",
    "gn:dem":5,
    "gn:feature_class":"P",
    "gn:feature_code":"PPL",
    "gn:name":"Ricanau Moffo",
    "gn:population":0,
    "gn:timezone":"America/Paramaribo",
    "iso:country":"SR",
    "name:und_x_variant":[
        "Rikanau",
        "Rikanaumoffo",
        "Ricanau Moffo"
    ],
    "wof:name":"Ricanau Moffo",
    "wof:placetype":"locality"
},
  "geometry": {"coordinates":[-54.41667,5.68333],"type":"Point"}
}