{
  "type": "Feature",
  "properties": {
    "gn:admin1_code":"11",
    "gn:asciiname":"Destombesburg",
    "gn:country_code":"SR",
    "gn:dem":17,
    "gn:feature_class":"P",
    "gn:feature_code":"PPL",
    "gn:name":"Destombesburg",
    "gn:population":0,
    "gn:timezone":"America/Paramaribo",
    "iso:country":"SR",
    "name:nld_x_preferred":[
        "Destombesburg"
    ],
    "wof:name":"Destombesburg",
    "wof:placetype":"locality"
},
  "geometry": {"coordinates":[-54.73087,5.6813],"type":"Point"}
}