{
  "type": "Feature",
  "properties": {
    "gn:admin1_code":"14",
    "gn:asciiname":"Utrecht",
    "gn:country_code":"SR",
    "gn:dem":6,
    "gn:feature_class":"P",
    "gn:feature_code":"PPL",
    "gn:name":"Utrecht",
    "gn:population":0,
    "gn:timezone":"America/Paramaribo",
    "iso:country":"SR",
    "name:nld_x_preferred":[
        "Utrecht"
    ],
    "wof:name":"Utrecht",
    "wof:placetype":"locality"
},
  "geometry": {"coordinates":[-56.66594,5.75102],"type":"Point"}
}