{
  "type": "Feature",
  "properties": {
    "gn:admin1_code":"13",
    "gn:asciiname":"Poelwijk",
    "gn:country_code":"SR",
    "gn:dem":18,
    "gn:feature_class":"P",
    "gn:feature_code":"PPL",
    "gn:name":"Poelwijk",
    "gn:population":0,
    "gn:timezone":"America/Paramaribo",
    "iso:country":"SR",
    "name:nld_x_preferred":[
        "Poelwijk"
    ],
    "wof:name":"Poelwijk",
    "wof:placetype":"locality"
},
  "geometry": {"coordinates":[-54.64928000000001,5.77116],"type":"Point"}
}