{
  "type": "Feature",
  "properties": {
    "gn:admin1_code":"14",
    "gn:asciiname":"Paradijs",
    "gn:country_code":"SR",
    "gn:dem":3,
    "gn:feature_class":"P",
    "gn:feature_code":"PPL",
    "gn:name":"Paradijs",
    "gn:population":0,
    "gn:timezone":"America/Paramaribo",
    "iso:country":"SR",
    "name:und_x_variant":[
        "Paradise"
    ],
    "wof:name":"Paradijs",
    "wof:placetype":"locality"
},
  "geometry": {"coordinates":[-56.90384,5.89783],"type":"Point"}
}