{
  "type": "Feature",
  "properties": {
    "gn:admin1_code":"14",
    "gn:asciiname":"Hertenrits",
    "gn:country_code":"SR",
    "gn:dem":-1,
    "gn:feature_class":"P",
    "gn:feature_code":"PPL",
    "gn:name":"Hertenrits",
    "gn:population":0,
    "gn:timezone":"America/Paramaribo",
    "iso:country":"SR",
    "name:nld_x_preferred":[
        "Hertenrits"
    ],
    "wof:name":"Hertenrits",
    "wof:placetype":"locality"
},
  "geometry": {"coordinates":[-56.64189,5.90478],"type":"Point"}
}