{
  "type": "Feature",
  "properties": {
    "gn:admin1_code":"14",
    "gn:asciiname":"Tapoeripa",
    "gn:country_code":"SR",
    "gn:dem":27,
    "gn:feature_class":"P",
    "gn:feature_code":"PPL",
    "gn:name":"Tapoeripa",
    "gn:population":0,
    "gn:timezone":"America/Paramaribo",
    "iso:country":"SR",
    "name:nld_x_preferred":[
        "Tapoeripa"
    ],
    "wof:name":"Tapoeripa",
    "wof:placetype":"locality"
},
  "geometry": {"coordinates":[-56.54258000000001,5.36771],"type":"Point"}
}