{
  "type": "Feature",
  "properties": {
    "gn:admin1_code":"18",
    "gn:asciiname":"Prodokaba",
    "gn:cc2":"SR",
    "gn:country_code":"SR",
    "gn:dem":89,
    "gn:feature_class":"P",
    "gn:feature_code":"PPL",
    "gn:name":"Prodokaba",
    "gn:population":0,
    "gn:timezone":"America/Paramaribo",
    "iso:country":"SR",
    "name:und_x_variant":[
        "Prodobaka",
        "Prodokaba"
    ],
    "wof:name":"Prodokaba",
    "wof:placetype":"locality"
},
  "geometry": {"coordinates":[-54.66667,4.11667],"type":"Point"}
}