{
  "type": "Feature",
  "properties": {
    "gn:admin1_code":"18",
    "gn:asciiname":"Matapi",
    "gn:country_code":"SR",
    "gn:dem":38,
    "gn:feature_class":"P",
    "gn:feature_code":"PPL",
    "gn:name":"Matapi",
    "gn:population":0,
    "gn:timezone":"America/Paramaribo",
    "iso:country":"SR",
    "name:und_x_variant":[
        "Matappi"
    ],
    "wof:name":"Matapi",
    "wof:placetype":"locality"
},
  "geometry": {"coordinates":[-57.2758,5.00217],"type":"Point"}
}