{
  "type": "Feature",
  "properties": {
    "gn:admin1_code":"11",
    "gn:asciiname":"Johannesburg",
    "gn:country_code":"SR",
    "gn:dem":1,
    "gn:feature_class":"P",
    "gn:feature_code":"PPL",
    "gn:name":"Johannesburg",
    "gn:population":0,
    "gn:timezone":"America/Paramaribo",
    "iso:country":"SR",
    "name:nld_x_preferred":[
        "Johannesburg"
    ],
    "wof:name":"Johannesburg",
    "wof:placetype":"locality"
},
  "geometry": {"coordinates":[-55.07098000000001,5.90666],"type":"Point"}
}